resoto_plugin_dockerhub/__init__.py
resoto_plugin_dockerhub/config.py
resoto_plugin_dockerhub/resources.py
resoto_plugin_dockerhub-3.9.0.dist-info/METADATA
resoto_plugin_dockerhub-3.9.0.dist-info/WHEEL
resoto_plugin_dockerhub-3.9.0.dist-info/entry_points.txt
resoto_plugin_dockerhub-3.9.0.dist-info/top_level.txt
resoto_plugin_dockerhub-3.9.0.dist-info/RECORD
