Metadata-Version: 2.1
Name: resoto-plugin-dockerhub
Version: 3.9.0
Summary: Resoto Docker Hub Collector Plugin
Author: Some Engineering Inc.
License: AGPLv3
Project-URL: Documentation, https://resoto.com
Project-URL: Source, https://github.com/someengineering/resoto/tree/main/plugins/dockerhub
Classifier: Development Status :: 4 - Beta
Classifier: Intended Audience :: System Administrators
Classifier: Intended Audience :: Information Technology
Classifier: License :: OSI Approved :: GNU Affero General Public License v3 or later (AGPLv3+)
Classifier: Programming Language :: Python :: 3.9
Classifier: Operating System :: POSIX :: Linux
Classifier: Operating System :: Unix
Classifier: Environment :: Console
Classifier: Natural Language :: English
Classifier: Topic :: Security
Classifier: Topic :: Utilities
Requires-Python: >=3.9
Requires-Dist: resotolib ==3.9.0
Requires-Dist: requests
